uspto_data/__init__.py
uspto_data/data_model.py
uspto_data/dataclass_generator.py
uspto_data/test.py
uspto_data/uspto_client.py
uspto_data/bulk_data/__init__.py
uspto_data/bulk_data/factory.py
uspto_data/bulk_data/fetcher.py
uspto_data/entities/__init__.py
uspto_data/entities/application.py
uspto_data/entities/patent.py
uspto_data/entities/publication.py
uspto_data/entities/content/__init__.py
uspto_data/entities/content/patent_content.py
uspto_data/entities/content/publication_content.py
uspto_data/google_patents/__init__.py
uspto_data/google_patents/adapter.py
uspto_data/google_patents/factory.py
uspto_data/google_patents/mock_client.py
uspto_data/google_patents/scraper.py
uspto_data/patentsview/__init__.py
uspto_data/patentsview/client.py
uspto_data/patentsview/endpoints.py
uspto_data/patentsview/query_builder.py
uspto_data/patentsview/response/__init__.py
uspto_data/patentsview/response/parser.py
uspto_data/query/__init__.py
uspto_data/query/builder.py
uspto_data/query/common.py
uspto_data/query/wrapper.py
uspto_data/response/__init__.py
uspto_data/response/response_interface.py
uspto_data/response/bulk_dataset/__endpoint__.py
uspto_data/response/bulk_dataset/__init__.py
uspto_data/response/bulk_dataset/products.py
uspto_data/response/bulk_dataset/search.py
uspto_data/response/bulk_dataset/ref/__init__.py
uspto_data/response/bulk_dataset/ref/download.py
uspto_data/response/bulk_dataset/ref/product_data.py
uspto_data/response/bulk_dataset/ref/search.py
uspto_data/response/patent_file_wrapper/__endpoint__.py
uspto_data/response/patent_file_wrapper/__init__.py
uspto_data/response/patent_file_wrapper/application.py
uspto_data/response/patent_file_wrapper/application_metadata.py
uspto_data/response/patent_file_wrapper/assignments.py
uspto_data/response/patent_file_wrapper/associated_documents.py
uspto_data/response/patent_file_wrapper/attorney.py
uspto_data/response/patent_file_wrapper/continuity.py
uspto_data/response/patent_file_wrapper/documents.py
uspto_data-0.1.7.dist-info/licenses/LICENSE
uspto_data-0.1.7.dist-info/METADATA
uspto_data-0.1.7.dist-info/WHEEL
uspto_data-0.1.7.dist-info/top_level.txt
uspto_data-0.1.7.dist-info/RECORD
