Metadata-Version: 2.4
Name: uspto-data
Version: 0.1.7
Summary: Structured Python datamodels and wrappers for accessing USPTO patent data APIs.
Home-page: https://forgen.ai
Author: ForGen AI, LLC
Author-email: support@forgen.ai
License: Proprietary
Classifier: License :: Other/Proprietary License
Classifier: Programming Language :: Python :: 3
Classifier: Programming Language :: Python :: 3.12
Classifier: Operating System :: OS Independent
Requires-Python: >=3.8
License-File: LICENSE
Requires-Dist: beautifulsoup4==4.13.4
Requires-Dist: blinker==1.9.0
Requires-Dist: certifi==2025.6.15
Requires-Dist: charset-normalizer==3.4.2
Requires-Dist: flask_requests==0.0.14
Requires-Dist: idna==3.10
Requires-Dist: pampy==0.3.0
Requires-Dist: requests==2.32.4
Requires-Dist: setuptools==80.9.0
Requires-Dist: soupsieve==2.7
Requires-Dist: typing_extensions==4.14.0
Requires-Dist: urllib3==2.5.0
Dynamic: author
Dynamic: author-email
Dynamic: classifier
Dynamic: description
Dynamic: description-content-type
Dynamic: home-page
Dynamic: license
Dynamic: license-file
Dynamic: requires-dist
Dynamic: requires-python
Dynamic: summary
